coco/__init__.py
coco/app.py
coco/constants.py
coco/exceptions.py
coco/loader.py
coco/pipelines.py
coco/model/__init__.py
coco/model/builder.py
coco/model/constants.py
coco/model/interface.py
coco/pagination/__init__.py
coco/pagination/builder.py
coco/pagination/constants.py
coco/pagination/interface.py
coco/stage/__init__.py
coco/stage/builder.py
coco/stage/constants.py
coco/stage/interface.py
coco/utils/__init__.py
coco/utils/request.py
coco/utils/timer.py
scrapy_coco-0.1.1.dist-info/LICENSE
scrapy_coco-0.1.1.dist-info/METADATA
scrapy_coco-0.1.1.dist-info/WHEEL
scrapy_coco-0.1.1.dist-info/top_level.txt
scrapy_coco-0.1.1.dist-info/RECORD
