Metadata-Version: 2.1
Name: scrapy-coco
Version: 0.1.1
Summary: Micro scraper framework
Home-page: https://github.com/pypa/sampleproject
Author: Giorgi Jambazishvili (m3ck0)
Author-email: m3ck0@pm.me
License: Type license() to see the full license text
Platform: UNKNOWN
Classifier: Programming Language :: Python :: 3
Classifier: License :: OSI Approved :: MIT License
Classifier: Operating System :: OS Independent
Requires-Python: >=3.8
Requires-Dist: aiohttp
Requires-Dist: beautifulsoup4
Requires-Dist: lxml
